<?xml version="1.0" encoding="UTF-8"?>

<!-- generated on 2024-07-25 16:06:56 by Eclipse SUMO GUI Version 1.19.0
<configuration xmlns:xsi="http://www.w3.org/2001/XMLSchema-instance" xsi:noNamespaceSchemaLocation="http://sumo.dlr.de/xsd/sumoConfiguration.xsd">

    <input>
        <net-file value="Network_Files_2/Traffic_Net.net.xml"/>
        <route-files value="Network_Files_2/Traffic_Net_Flow.rou.xml"/>
        <additional-files value="Network_Files_2/Traffic_Net.add.xml"/>
        <junction-taz value="true"/>
    </input>

    <output>
        <output-prefix value="Loop_Data_Ramp_ALIANA/"/>
    </output>

    <time>
        <begin value="0"/>
        <end value="14400"/>
    </time>

    <processing>
        <time-to-teleport value="300"/>
    </processing>

    <traci_server>
        <remote-port value="54011"/>
    </traci_server>

</configuration>
-->

<detector xmlns:xsi="http://www.w3.org/2001/XMLSchema-instance" xsi:noNamespaceSchemaLocation="http://sumo.dlr.de/xsd/det_e1_file.xsd">
    <interval begin="0.00" end="60.00" id="H10E_4_0" nVehContrib="0" flow="0.00" occupancy="0.00" speed="-1.00" harmonicMeanSpeed="-1.00" length="-1.00" nVehEntered="0"/>
    <interval begin="60.00" end="120.00" id="H10E_4_0" nVehContrib="1" flow="60.00" occupancy="0.34" speed="24.16" harmonicMeanSpeed="24.16" length="5.00" nVehEntered="1"/>
    <interval begin="120.00" end="180.00" id="H10E_4_0" nVehContrib="2" flow="120.00" occupancy="0.69" speed="24.23" harmonicMeanSpeed="24.21" length="5.00" nVehEntered="2"/>
    <interval begin="180.00" end="240.00" id="H10E_4_0" nVehContrib="2" flow="120.00" occupancy="0.87" speed="19.65" harmonicMeanSpeed="19.07" length="5.00" nVehEntered="2"/>
    <interval begin="240.00" end="300.00" id="H10E_4_0" nVehContrib="5" flow="300.00" occupancy="2.69" speed="16.34" harmonicMeanSpeed="15.49" length="5.00" nVehEntered="5"/>
    <interval begin="300.00" end="360.00" id="H10E_4_0" nVehContrib="2" flow="120.00" occupancy="0.97" speed="17.20" harmonicMeanSpeed="17.19" length="5.00" nVehEntered="2"/>
    <interval begin="360.00" end="420.00" id="H10E_4_0" nVehContrib="1" flow="60.00" occupancy="0.41" speed="20.56" harmonicMeanSpeed="20.56" length="5.00" nVehEntered="1"/>
    <interval begin="420.00" end="480.00" id="H10E_4_0" nVehContrib="1" flow="60.00" occupancy="0.74" speed="18.55" harmonicMeanSpeed="18.55" length="5.00" nVehEntered="2"/>
    <interval begin="480.00" end="540.00" id="H10E_4_0" nVehContrib="5" flow="300.00" occupancy="2.40" speed="17.60" harmonicMeanSpeed="17.38" length="5.00" nVehEntered="5"/>
    <interval begin="540.00" end="600.00" id="H10E_4_0" nVehContrib="0" flow="0.00" occupancy="0.00" speed="-1.00" harmonicMeanSpeed="-1.00" length="-1.00" nVehEntered="0"/>
    <interval begin="600.00" end="660.00" id="H10E_4_0" nVehContrib="0" flow="0.00" occupancy="0.00" speed="-1.00" harmonicMeanSpeed="-1.00" length="-1.00" nVehEntered="0"/>
    <interval begin="660.00" end="720.00" id="H10E_4_0" nVehContrib="2" flow="120.00" occupancy="0.93" speed="18.09" harmonicMeanSpeed="18.01" length="5.00" nVehEntered="2"/>
    <interval begin="720.00" end="780.00" id="H10E_4_0" nVehContrib="0" flow="0.00" occupancy="0.00" speed="-1.00" harmonicMeanSpeed="-1.00" length="-1.00" nVehEntered="0"/>
    <interval begin="780.00" end="840.00" id="H10E_4_0" nVehContrib="2" flow="120.00" occupancy="1.18" speed="14.88" harmonicMeanSpeed="14.88" length="5.00" nVehEntered="3"/>
    <interval begin="840.00" end="900.00" id="H10E_4_0" nVehContrib="3" flow="180.00" occupancy="1.81" speed="15.67" harmonicMeanSpeed="15.04" length="5.00" nVehEntered="4"/>
    <interval begin="900.00" end="960.00" id="H10E_4_0" nVehContrib="1" flow="60.00" occupancy="0.56" speed="17.92" harmonicMeanSpeed="17.92" length="5.00" nVehEntered="2"/>
    <interval begin="960.00" end="1020.00" id="H10E_4_0" nVehContrib="1" flow="60.00" occupancy="0.69" speed="19.20" harmonicMeanSpeed="19.20" length="5.00" nVehEntered="2"/>
    <interval begin="1020.00" end="1080.00" id="H10E_4_0" nVehContrib="2" flow="120.00" occupancy="1.19" speed="14.37" harmonicMeanSpeed="14.00" length="5.00" nVehEntered="2"/>
    <interval begin="1080.00" end="1140.00" id="H10E_4_0" nVehContrib="1" flow="60.00" occupancy="0.51" speed="16.20" harmonicMeanSpeed="16.20" length="5.00" nVehEntered="1"/>
    <interval begin="1140.00" end="1200.00" id="H10E_4_0" nVehContrib="1" flow="60.00" occupancy="0.42" speed="20.06" harmonicMeanSpeed="20.06" length="5.00" nVehEntered="1"/>
    <interval begin="1200.00" end="1260.00" id="H10E_4_0" nVehContrib="1" flow="60.00" occupancy="0.46" speed="17.98" harmonicMeanSpeed="17.98" length="5.00" nVehEntered="1"/>
    <interval begin="1260.00" end="1320.00" id="H10E_4_0" nVehContrib="1" flow="60.00" occupancy="0.47" speed="17.57" harmonicMeanSpeed="17.57" length="5.00" nVehEntered="1"/>
    <interval begin="1320.00" end="1380.00" id="H10E_4_0" nVehContrib="5" flow="300.00" occupancy="2.41" speed="17.65" harmonicMeanSpeed="17.29" length="5.00" nVehEntered="5"/>
    <interval begin="1380.00" end="1440.00" id="H10E_4_0" nVehContrib="3" flow="180.00" occupancy="1.31" speed="19.26" harmonicMeanSpeed="19.15" length="5.00" nVehEntered="3"/>
    <interval begin="1440.00" end="1500.00" id="H10E_4_0" nVehContrib="2" flow="120.00" occupancy="1.33" speed="17.68" harmonicMeanSpeed="17.65" length="5.00" nVehEntered="3"/>
    <interval begin="1500.00" end="1560.00" id="H10E_4_0" nVehContrib="4" flow="240.00" occupancy="1.84" speed="18.35" harmonicMeanSpeed="18.10" length="5.00" nVehEntered="4"/>
    <interval begin="1560.00" end="1620.00" id="H10E_4_0" nVehContrib="2" flow="120.00" occupancy="1.14" speed="14.88" harmonicMeanSpeed="14.59" length="5.00" nVehEntered="2"/>
    <interval begin="1620.00" end="1680.00" id="H10E_4_0" nVehContrib="3" flow="180.00" occupancy="1.34" speed="18.91" harmonicMeanSpeed="18.64" length="5.00" nVehEntered="3"/>
    <interval begin="1680.00" end="1740.00" id="H10E_4_0" nVehContrib="3" flow="180.00" occupancy="1.55" speed="16.42" harmonicMeanSpeed="16.10" length="5.00" nVehEntered="3"/>
    <interval begin="1740.00" end="1800.00" id="H10E_4_0" nVehContrib="1" flow="60.00" occupancy="1.04" speed="15.05" harmonicMeanSpeed="15.05" length="5.00" nVehEntered="3"/>
    <interval begin="1800.00" end="1860.00" id="H10E_4_0" nVehContrib="3" flow="180.00" occupancy="1.47" speed="18.22" harmonicMeanSpeed="17.06" length="5.00" nVehEntered="3"/>
    <interval begin="1860.00" end="1920.00" id="H10E_4_0" nVehContrib="0" flow="0.00" occupancy="0.00" speed="-1.00" harmonicMeanSpeed="-1.00" length="-1.00" nVehEntered="0"/>
    <interval begin="1920.00" end="1980.00" id="H10E_4_0" nVehContrib="3" flow="180.00" occupancy="2.13" speed="14.55" harmonicMeanSpeed="11.76" length="5.00" nVehEntered="3"/>
    <interval begin="1980.00" end="2040.00" id="H10E_4_0" nVehContrib="2" flow="120.00" occupancy="0.90" speed="18.49" harmonicMeanSpeed="18.49" length="5.00" nVehEntered="2"/>
    <interval begin="2040.00" end="2100.00" id="H10E_4_0" nVehContrib="0" flow="0.00" occupancy="0.00" speed="-1.00" harmonicMeanSpeed="-1.00" length="-1.00" nVehEntered="0"/>
    <interval begin="2100.00" end="2160.00" id="H10E_4_0" nVehContrib="2" flow="120.00" occupancy="0.92" speed="18.31" harmonicMeanSpeed="18.16" length="5.00" nVehEntered="2"/>
    <interval begin="2160.00" end="2220.00" id="H10E_4_0" nVehContrib="2" flow="120.00" occupancy="0.88" speed="19.21" harmonicMeanSpeed="18.85" length="5.00" nVehEntered="2"/>
    <interval begin="2220.00" end="2280.00" id="H10E_4_0" nVehContrib="4" flow="240.00" occupancy="1.74" speed="19.13" harmonicMeanSpeed="19.12" length="5.00" nVehEntered="4"/>
    <interval begin="2280.00" end="2340.00" id="H10E_4_0" nVehContrib="0" flow="0.00" occupancy="0.00" speed="-1.00" harmonicMeanSpeed="-1.00" length="-1.00" nVehEntered="0"/>
    <interval begin="2340.00" end="2400.00" id="H10E_4_0" nVehContrib="1" flow="60.00" occupancy="0.50" speed="16.83" harmonicMeanSpeed="16.83" length="5.00" nVehEntered="1"/>
    <interval begin="2400.00" end="2460.00" id="H10E_4_0" nVehContrib="2" flow="120.00" occupancy="0.89" speed="18.92" harmonicMeanSpeed="18.82" length="5.00" nVehEntered="2"/>
    <interval begin="2460.00" end="2520.00" id="H10E_4_0" nVehContrib="9" flow="540.00" occupancy="4.30" speed="17.74" harmonicMeanSpeed="17.46" length="5.00" nVehEntered="9"/>
    <interval begin="2520.00" end="2580.00" id="H10E_4_0" nVehContrib="3" flow="180.00" occupancy="1.48" speed="17.19" harmonicMeanSpeed="16.84" length="5.00" nVehEntered="3"/>
    <interval begin="2580.00" end="2640.00" id="H10E_4_0" nVehContrib="1" flow="60.00" occupancy="0.42" speed="19.78" harmonicMeanSpeed="19.78" length="5.00" nVehEntered="1"/>
    <interval begin="2640.00" end="2700.00" id="H10E_4_0" nVehContrib="0" flow="0.00" occupancy="0.00" speed="-1.00" harmonicMeanSpeed="-1.00" length="-1.00" nVehEntered="0"/>
    <interval begin="2700.00" end="2760.00" id="H10E_4_0" nVehContrib="0" flow="0.00" occupancy="0.00" speed="-1.00" harmonicMeanSpeed="-1.00" length="-1.00" nVehEntered="0"/>
    <interval begin="2760.00" end="2820.00" id="H10E_4_0" nVehContrib="0" flow="0.00" occupancy="0.38" speed="-1.00" harmonicMeanSpeed="-1.00" length="-1.00" nVehEntered="1"/>
    <interval begin="2820.00" end="2880.00" id="H10E_4_0" nVehContrib="1" flow="60.00" occupancy="0.45" speed="18.34" harmonicMeanSpeed="18.34" length="5.00" nVehEntered="1"/>
    <interval begin="2880.00" end="2940.00" id="H10E_4_0" nVehContrib="1" flow="60.00" occupancy="0.41" speed="20.56" harmonicMeanSpeed="20.56" length="5.00" nVehEntered="1"/>
    <interval begin="2940.00" end="3000.00" id="H10E_4_0" nVehContrib="3" flow="180.00" occupancy="1.37" speed="18.39" harmonicMeanSpeed="18.30" length="5.00" nVehEntered="3"/>
    <interval begin="3000.00" end="3060.00" id="H10E_4_0" nVehContrib="3" flow="180.00" occupancy="1.44" speed="17.40" harmonicMeanSpeed="17.36" length="5.00" nVehEntered="3"/>
    <interval begin="3060.00" end="3120.00" id="H10E_4_0" nVehContrib="2" flow="120.00" occupancy="0.83" speed="20.09" harmonicMeanSpeed="20.09" length="5.00" nVehEntered="2"/>
    <interval begin="3120.00" end="3180.00" id="H10E_4_0" nVehContrib="2" flow="120.00" occupancy="0.83" speed="20.11" harmonicMeanSpeed="20.09" length="5.00" nVehEntered="2"/>
    <interval begin="3180.00" end="3240.00" id="H10E_4_0" nVehContrib="0" flow="0.00" occupancy="0.46" speed="-1.00" harmonicMeanSpeed="-1.00" length="-1.00" nVehEntered="1"/>
    <interval begin="3240.00" end="3300.00" id="H10E_4_0" nVehContrib="2" flow="120.00" occupancy="1.05" speed="16.07" harmonicMeanSpeed="15.89" length="5.00" nVehEntered="2"/>
    <interval begin="3300.00" end="3360.00" id="H10E_4_0" nVehContrib="2" flow="120.00" occupancy="0.88" speed="18.95" harmonicMeanSpeed="18.95" length="5.00" nVehEntered="2"/>
    <interval begin="3360.00" end="3420.00" id="H10E_4_0" nVehContrib="1" flow="60.00" occupancy="0.51" speed="16.34" harmonicMeanSpeed="16.34" length="5.00" nVehEntered="1"/>
    <interval begin="3420.00" end="3480.00" id="H10E_4_0" nVehContrib="3" flow="180.00" occupancy="1.41" speed="17.98" harmonicMeanSpeed="17.75" length="5.00" nVehEntered="3"/>
    <interval begin="3480.00" end="3540.00" id="H10E_4_0" nVehContrib="2" flow="120.00" occupancy="1.24" speed="13.56" harmonicMeanSpeed="13.43" length="5.00" nVehEntered="2"/>
    <interval begin="3540.00" end="3600.00" id="H10E_4_0" nVehContrib="2" flow="120.00" occupancy="0.85" speed="19.79" harmonicMeanSpeed="19.70" length="5.00" nVehEntered="2"/>
    <interval begin="3600.00" end="3660.00" id="H10E_4_0" nVehContrib="2" flow="120.00" occupancy="0.81" speed="20.54" harmonicMeanSpeed="20.52" length="5.00" nVehEntered="2"/>
    <interval begin="3660.00" end="3682.00" id="H10E_4_0" nVehContrib="0" flow="0.00" occupancy="0.00" speed="-1.00" harmonicMeanSpeed="-1.00" length="-1.00" nVehEntered="0"/>
</detector>
