<?xml version="1.0" encoding="UTF-8"?>

<!-- generated on 2024-06-04 11:45:37 by Eclipse SUMO GUI Version 1.19.0
<configuration xmlns:xsi="http://www.w3.org/2001/XMLSchema-instance" xsi:noNamespaceSchemaLocation="http://sumo.dlr.de/xsd/sumoConfiguration.xsd">

    <input>
        <net-file value="Network_Files/Traffic_Net.net.xml"/>
        <route-files value="Network_Files/Traffic_Net_Flow.rou.xml"/>
        <additional-files value="Network_Files/Traffic_Net.add.xml"/>
        <junction-taz value="true"/>
    </input>

    <time>
        <begin value="0"/>
        <end value="14400"/>
    </time>

</configuration>
-->

<detector xmlns:xsi="http://www.w3.org/2001/XMLSchema-instance" xsi:noNamespaceSchemaLocation="http://sumo.dlr.de/xsd/det_e1_file.xsd">
    <interval begin="0.00" end="300.00" id="H20E_out_1" nVehContrib="3" flow="36.00" occupancy="0.37" speed="13.72" harmonicMeanSpeed="13.48" length="5.00" nVehEntered="3"/>
    <interval begin="300.00" end="600.00" id="H20E_out_1" nVehContrib="54" flow="648.00" occupancy="7.23" speed="12.57" harmonicMeanSpeed="12.44" length="5.00" nVehEntered="54"/>
    <interval begin="600.00" end="900.00" id="H20E_out_1" nVehContrib="102" flow="1224.00" occupancy="13.96" speed="12.31" harmonicMeanSpeed="12.18" length="5.00" nVehEntered="102"/>
    <interval begin="900.00" end="1200.00" id="H20E_out_1" nVehContrib="100" flow="1200.00" occupancy="13.23" speed="12.69" harmonicMeanSpeed="12.60" length="5.00" nVehEntered="100"/>
    <interval begin="1200.00" end="1500.00" id="H20E_out_1" nVehContrib="101" flow="1212.00" occupancy="13.62" speed="12.52" harmonicMeanSpeed="12.44" length="5.00" nVehEntered="102"/>
    <interval begin="1500.00" end="1800.00" id="H20E_out_1" nVehContrib="98" flow="1176.00" occupancy="13.49" speed="12.18" harmonicMeanSpeed="12.03" length="5.00" nVehEntered="97"/>
    <interval begin="1800.00" end="2100.00" id="H20E_out_1" nVehContrib="95" flow="1140.00" occupancy="13.30" speed="12.21" harmonicMeanSpeed="11.90" length="5.00" nVehEntered="95"/>
    <interval begin="2100.00" end="2400.00" id="H20E_out_1" nVehContrib="42" flow="504.00" occupancy="5.13" speed="13.74" harmonicMeanSpeed="13.67" length="5.00" nVehEntered="43"/>
    <interval begin="2400.00" end="2700.00" id="H20E_out_1" nVehContrib="36" flow="432.00" occupancy="4.62" speed="13.11" harmonicMeanSpeed="12.99" length="5.00" nVehEntered="36"/>
    <interval begin="2700.00" end="3000.00" id="H20E_out_1" nVehContrib="27" flow="324.00" occupancy="3.70" speed="13.13" harmonicMeanSpeed="12.15" length="5.00" nVehEntered="28"/>
    <interval begin="3000.00" end="3300.00" id="H20E_out_1" nVehContrib="25" flow="300.00" occupancy="3.02" speed="13.88" harmonicMeanSpeed="13.79" length="5.00" nVehEntered="25"/>
    <interval begin="3300.00" end="3600.00" id="H20E_out_1" nVehContrib="50" flow="600.00" occupancy="6.21" speed="13.56" harmonicMeanSpeed="13.43" length="5.00" nVehEntered="50"/>
    <interval begin="3600.00" end="3900.00" id="H20E_out_1" nVehContrib="19" flow="228.00" occupancy="2.42" speed="13.25" harmonicMeanSpeed="13.11" length="5.00" nVehEntered="19"/>
    <interval begin="3900.00" end="4200.00" id="H20E_out_1" nVehContrib="39" flow="468.00" occupancy="4.64" speed="14.13" harmonicMeanSpeed="14.01" length="5.00" nVehEntered="39"/>
    <interval begin="4200.00" end="4500.00" id="H20E_out_1" nVehContrib="16" flow="192.00" occupancy="1.92" speed="14.03" harmonicMeanSpeed="13.89" length="5.00" nVehEntered="16"/>
    <interval begin="4500.00" end="4800.00" id="H20E_out_1" nVehContrib="43" flow="516.00" occupancy="5.31" speed="13.58" harmonicMeanSpeed="13.51" length="5.00" nVehEntered="43"/>
    <interval begin="4800.00" end="5100.00" id="H20E_out_1" nVehContrib="14" flow="168.00" occupancy="1.63" speed="14.42" harmonicMeanSpeed="14.32" length="5.00" nVehEntered="14"/>
    <interval begin="5100.00" end="5400.00" id="H20E_out_1" nVehContrib="49" flow="588.00" occupancy="6.19" speed="13.27" harmonicMeanSpeed="13.18" length="5.00" nVehEntered="49"/>
    <interval begin="5400.00" end="5700.00" id="H20E_out_1" nVehContrib="30" flow="360.00" occupancy="3.96" speed="13.29" harmonicMeanSpeed="12.63" length="5.00" nVehEntered="30"/>
    <interval begin="5700.00" end="6000.00" id="H20E_out_1" nVehContrib="24" flow="288.00" occupancy="3.23" speed="13.38" harmonicMeanSpeed="12.37" length="5.00" nVehEntered="24"/>
    <interval begin="6000.00" end="6300.00" id="H20E_out_1" nVehContrib="1" flow="12.00" occupancy="0.11" speed="15.43" harmonicMeanSpeed="15.43" length="5.00" nVehEntered="1"/>
    <interval begin="6300.00" end="6600.00" id="H20E_out_1" nVehContrib="11" flow="132.00" occupancy="1.32" speed="13.97" harmonicMeanSpeed="13.92" length="5.00" nVehEntered="11"/>
    <interval begin="6600.00" end="6780.00" id="H20E_out_1" nVehContrib="4" flow="80.00" occupancy="0.83" speed="13.52" harmonicMeanSpeed="13.44" length="5.00" nVehEntered="4"/>
</detector>
