<?xml version="1.0" encoding="UTF-8"?>

<!-- generated on 2024-07-04 22:52:35 by Eclipse SUMO GUI Version 1.20.0
<configuration xmlns:xsi="http://www.w3.org/2001/XMLSchema-instance" xsi:noNamespaceSchemaLocation="http://sumo.dlr.de/xsd/sumoConfiguration.xsd">

    <input>
        <net-file value="Network_Files/Traffic_Net.net.xml"/>
        <route-files value="Network_Files/Traffic_Net_Flow.rou.xml"/>
        <additional-files value="Network_Files/Traffic_Net.add.xml"/>
        <junction-taz value="true"/>
    </input>

    <output>
        <output-prefix value="Loop_Data_Ramp_Open/"/>
    </output>

    <time>
        <begin value="0"/>
        <end value="14400"/>
    </time>

    <traci_server>
        <remote-port value="55028"/>
    </traci_server>

</configuration>
-->

<detector xmlns:xsi="http://www.w3.org/2001/XMLSchema-instance" xsi:noNamespaceSchemaLocation="http://sumo.dlr.de/xsd/det_e1_file.xsd">
    <interval begin="0.00" end="180.00" id="H15N_1_0" nVehContrib="26" flow="520.00" occupancy="2.51" speed="28.96" harmonicMeanSpeed="28.74" length="5.00" nVehEntered="26"/>
    <interval begin="180.00" end="360.00" id="H15N_1_0" nVehContrib="70" flow="1400.00" occupancy="6.93" speed="28.23" harmonicMeanSpeed="28.05" length="5.00" nVehEntered="70"/>
    <interval begin="360.00" end="540.00" id="H15N_1_0" nVehContrib="68" flow="1360.00" occupancy="6.75" speed="28.16" harmonicMeanSpeed="27.98" length="5.00" nVehEntered="68"/>
    <interval begin="540.00" end="720.00" id="H15N_1_0" nVehContrib="73" flow="1460.00" occupancy="7.26" speed="28.43" harmonicMeanSpeed="28.19" length="5.00" nVehEntered="74"/>
    <interval begin="720.00" end="888.00" id="H15N_1_0" nVehContrib="78" flow="1671.43" occupancy="8.86" speed="26.34" harmonicMeanSpeed="26.20" length="5.00" nVehEntered="78"/>
</detector>
