<?xml version="1.0" encoding="UTF-8"?>

<!-- generated on 2024-07-04 22:52:35 by Eclipse SUMO GUI Version 1.20.0
<configuration xmlns:xsi="http://www.w3.org/2001/XMLSchema-instance" xsi:noNamespaceSchemaLocation="http://sumo.dlr.de/xsd/sumoConfiguration.xsd">

    <input>
        <net-file value="Network_Files/Traffic_Net.net.xml"/>
        <route-files value="Network_Files/Traffic_Net_Flow.rou.xml"/>
        <additional-files value="Network_Files/Traffic_Net.add.xml"/>
        <junction-taz value="true"/>
    </input>

    <output>
        <output-prefix value="Loop_Data_Ramp_Open/"/>
    </output>

    <time>
        <begin value="0"/>
        <end value="14400"/>
    </time>

    <traci_server>
        <remote-port value="55028"/>
    </traci_server>

</configuration>
-->

<detector xmlns:xsi="http://www.w3.org/2001/XMLSchema-instance" xsi:noNamespaceSchemaLocation="http://sumo.dlr.de/xsd/det_e1_file.xsd">
    <interval begin="0.00" end="180.00" id="H15N_1_1" nVehContrib="60" flow="1200.00" occupancy="5.56" speed="30.22" harmonicMeanSpeed="29.99" length="5.00" nVehEntered="60"/>
    <interval begin="180.00" end="360.00" id="H15N_1_1" nVehContrib="88" flow="1760.00" occupancy="8.57" speed="28.99" harmonicMeanSpeed="28.83" length="5.00" nVehEntered="90"/>
    <interval begin="360.00" end="540.00" id="H15N_1_1" nVehContrib="91" flow="1820.00" occupancy="8.73" speed="29.17" harmonicMeanSpeed="28.96" length="5.00" nVehEntered="91"/>
    <interval begin="540.00" end="720.00" id="H15N_1_1" nVehContrib="90" flow="1800.00" occupancy="9.29" speed="28.57" harmonicMeanSpeed="27.11" length="5.00" nVehEntered="91"/>
    <interval begin="720.00" end="888.00" id="H15N_1_1" nVehContrib="96" flow="2057.14" occupancy="11.05" speed="27.04" harmonicMeanSpeed="25.86" length="5.00" nVehEntered="97"/>
</detector>
